modularis/__init__.py
modularis/cache.py
modularis/client.py
modularis/client_new.py
modularis/compression.py
modularis/encryption.py
modularis/interceptor.py
modularis/metrics.py
modularis/middleware.py
modularis/response.py
modularis/serializer.py
modularis/validator.py
modularis-0.1.1.dist-info/LICENSE
modularis-0.1.1.dist-info/METADATA
modularis-0.1.1.dist-info/WHEEL
modularis-0.1.1.dist-info/top_level.txt
modularis-0.1.1.dist-info/RECORD
