Metadata-Version: 2.1
Name: modularis
Version: 0.1.1
Summary: A Modern, High-Performance HTTP Client Library for Python
Home-page: https://github.com/hexakleo/modularis
Author: Pandaxyz-xd
Author-email: Pandaxyz-xd <hexakleo@gmail.com>
License: MIT License
Project-URL: Homepage, https://github.com/hexakleo/modularis
Project-URL: Documentation, https://modularis.readthedocs.io/
Project-URL: Repository, https://github.com/hexakleo/modularis.git
Project-URL: Bug Tracker, https://github.com/hexakleo/modularis/issues
Keywords: http,client,async,aiohttp,api
Classifier: Development Status :: 4 - Beta
Classifier: Intended Audience :: Developers
Classifier: License :: OSI Approved :: MIT License
Classifier: Operating System :: OS Independent
Classifier: Programming Language :: Python :: 3
Classifier: Programming Language :: Python :: 3.8
Classifier: Programming Language :: Python :: 3.9
Classifier: Programming Language :: Python :: 3.10
Classifier: Programming Language :: Python :: 3.11
Classifier: Topic :: Internet :: WWW/HTTP
Classifier: Topic :: Software Development :: Libraries :: Python Modules
Requires-Python: >=3.8
License-File: LICENSE
Requires-Dist: aiohttp>=3.8.0
Requires-Dist: pydantic>=2.0.0
Requires-Dist: typing-extensions>=4.0.0
Requires-Dist: python-dateutil>=2.8.0
Requires-Dist: jsonschema>=4.0.0
Requires-Dist: python-jose[cryptography]>=3.3.0
Requires-Dist: python-multipart>=0.0.5
